aiolos_cfd_tools/__init__.py
aiolos_cfd_tools/cfd_maths.py
aiolos_code_instrumentation/__init__.py
aiolos_code_instrumentation/add_logging_level.py
aiolos_code_instrumentation/renamer.py
aiolos_code_instrumentation/timer/__init__.py
aiolos_code_instrumentation/timer/timer.py
aiolos_commissioning_tools/__init__.py
aiolos_commissioning_tools/hotwire.py
aiolos_commissioning_tools/pressure.py
aiolos_commissioning_tools/tunnel_conditions.py
aiolos_fluid_dynamics/__init__.py
aiolos_fluid_dynamics/fluid_dynamics_relationships.py
aiolos_fluid_dynamics/physical_constants.py
aiolos_fluid_dynamics/units.py
aiolos_plotting/__init__.py
aiolos_plotting/bokeh_plots.py
aiolos_plotting/plot_pressures.py
aiolos_plotting/plotting.py
aiolos_tools-0.2.4.dist-info/LICENSE
aiolos_tools-0.2.4.dist-info/METADATA
aiolos_tools-0.2.4.dist-info/WHEEL
aiolos_tools-0.2.4.dist-info/top_level.txt
aiolos_tools-0.2.4.dist-info/RECORD
